cli/__init__.py
cli/commands.py
core/__init__.py
core/security.py
core/storage.py
vlt_cli-1.0.1.dist-info/METADATA
vlt_cli-1.0.1.dist-info/WHEEL
vlt_cli-1.0.1.dist-info/entry_points.txt
vlt_cli-1.0.1.dist-info/top_level.txt
vlt_cli-1.0.1.dist-info/RECORD
