Metadata-Version: 2.4
Name: vlt-cli
Version: 1.0.1
Summary: Enterprise-grade secure environment variable manager with AES-256 encryption
Author-email: FARYAD ALI <faryadali14pk@gmail.com>
License: MIT
Project-URL: Homepage, https://github.com/faryadali/vlt-cli
Project-URL: Documentation, https://github.com/faryadali/vlt-cli#readme
Project-URL: Repository, https://github.com/faryadali/vlt-cli
Project-URL: Issues, https://github.com/faryadali/vlt-cli/issues
Keywords: security,encryption,environment-variables,cli,vault,secrets-management
Classifier: Development Status :: 4 - Beta
Classifier: Intended Audience :: Developers
Classifier: Topic :: Security :: Cryptography
Classifier: Topic :: Software Development :: Build Tools
Classifier: License :: OSI Approved :: MIT License
Classifier: Programming Language :: Python :: 3
Classifier: Programming Language :: Python :: 3.8
Classifier: Programming Language :: Python :: 3.9
Classifier: Programming Language :: Python :: 3.10
Classifier: Programming Language :: Python :: 3.11
Classifier: Operating System :: OS Independent
Requires-Python: >=3.8
Requires-Dist: cryptography>=41.0.0
Requires-Dist: click>=8.1.7
Requires-Dist: colorama>=0.4.6
Requires-Dist: pyyaml>=6.0.1
Requires-Dist: python-dotenv>=1.0.0
Requires-Dist: tabulate>=0.9.0
Provides-Extra: dev
Requires-Dist: pytest>=7.4.3; extra == "dev"
Requires-Dist: pytest-cov>=4.1.0; extra == "dev"
Requires-Dist: black>=23.0.0; extra == "dev"
Requires-Dist: flake8>=6.0.0; extra == "dev"
